heatequation.py
heatequation-1.0.0.dist-info/DESCRIPTION.rst
heatequation-1.0.0.dist-info/METADATA
heatequation-1.0.0.dist-info/RECORD
heatequation-1.0.0.dist-info/WHEEL
heatequation-1.0.0.dist-info/metadata.json
heatequation-1.0.0.dist-info/top_level.txt
