Metadata-Version: 2.0
Name: heatequation
Version: 1.0.0
Summary: Calculate heat transfer in a matrix of heterogeneous materials
Home-page: https://github.com/worden341/heatequation
Author: Eric Worden
Author-email: UNKNOWN
License: GPL-3.0+
Keywords: heat equation thermal transfer
Platform: UNKNOWN
Classifier: Development Status :: 4 - Beta
Classifier: Intended Audience :: Developers
Classifier: Operating System :: OS Independent
Classifier: Topic :: Software Development :: Libraries :: Python Modules
Classifier: Topic :: Scientific/Engineering :: Physics
Classifier: Programming Language :: Python :: 2
Classifier: Programming Language :: Python :: 2.7
Classifier: Programming Language :: Python :: 3
Classifier: Natural Language :: English
Classifier: License :: OSI Approved :: GNU General Public License v3 or later (GPLv3+)
Requires-Python: >=2.7
Requires-Dist: scipy
